odoo/addons/repair_order_template/README.rst
odoo/addons/repair_order_template/__init__.py
odoo/addons/repair_order_template/__manifest__.py
odoo/addons/repair_order_template/demo/repair_order_template.xml
odoo/addons/repair_order_template/i18n/it.po
odoo/addons/repair_order_template/i18n/repair_order_template.pot
odoo/addons/repair_order_template/models/__init__.py
odoo/addons/repair_order_template/models/repair_order.py
odoo/addons/repair_order_template/models/repair_order_template.py
odoo/addons/repair_order_template/models/repair_order_template_line.py
odoo/addons/repair_order_template/readme/CONFIGURE.md
odoo/addons/repair_order_template/readme/CONTRIBUTORS.md
odoo/addons/repair_order_template/readme/DESCRIPTION.md
odoo/addons/repair_order_template/readme/USAGE.md
odoo/addons/repair_order_template/security/ir.model.access.csv
odoo/addons/repair_order_template/security/security.xml
odoo/addons/repair_order_template/static/description/icon.png
odoo/addons/repair_order_template/static/description/index.html
odoo/addons/repair_order_template/tests/__init__.py
odoo/addons/repair_order_template/tests/test_repair_order_template.py
odoo/addons/repair_order_template/views/repair_order.xml
odoo/addons/repair_order_template/views/repair_order_template.xml
odoo_addon_repair_order_template-18.0.1.0.1.dist-info/METADATA
odoo_addon_repair_order_template-18.0.1.0.1.dist-info/WHEEL
odoo_addon_repair_order_template-18.0.1.0.1.dist-info/top_level.txt
odoo_addon_repair_order_template-18.0.1.0.1.dist-info/RECORD
